searchlix/__init__.py
searchlix/searchlix.py
searchlix-1.0.7.dist-info/METADATA
searchlix-1.0.7.dist-info/WHEEL
searchlix-1.0.7.dist-info/top_level.txt
searchlix-1.0.7.dist-info/RECORD
