Metadata-Version: 2.1
Name: searchlix
Version: 1.0.7
Summary: A package for extract data from websites and text
Home-page: UNKNOWN
Author: Hashem
Author-email: hashem.a.muhammad@gmail.com
License: UNKNOWN
Keywords: python,web scraping,emails,phone,data,search,extract data
Platform: UNKNOWN
Requires-Dist: requests
Requires-Dist: beautifulsoup4
Requires-Dist: dnspython (==2.3.0)
